{"O0":{"WebAssemblyCollectedTimes":[{"filesFound":0,"altered":true,"WasmFiles":{"d9bcc02f1f1c5cf990bc2b0ef86dbe69d32bf7db37c27cffcb2e62848c6820f8":{"instantiate":[{"Start":55.5249999742955,"End":55.95000000903383,"Duration":0.42500003473833203}],"compile":[{"Start":50.389999989420176,"End":55.47999998088926,"Duration":5.089999991469085}],"exportCalls":{"__wasm_call_ctors":[{"Start":57.49999999534339,"End":57.50499997520819,"Duration":0.004999979864805937}],"stackAlloc":[{"Start":57.595000020228326,"End":57.595000020228326,"Duration":0},{"Start":57.64499999349937,"End":57.64499999349937,"Duration":0}],"main":[{"Start":57.730000000447035,"End":122.43499996839091,"Duration":64.70499996794388}]},"importCalls":{},"functionNameObjects":[],"addExport":{},"addImport":{},"addInstantiate":{},"addInstantiateStreaming":{},"addCompile":{},"addCompileStreaming":{},"addFunctionNames":{}}},"addWasmFileReference":{}},{"filesFound":0,"altered":true,"WasmFiles":{"d9bcc02f1f1c5cf990bc2b0ef86dbe69d32bf7db37c27cffcb2e62848c6820f8":{"instantiate":[{"Start":69.0850000246428,"End":69.46000002790242,"Duration":0.375000003259629}],"compile":[{"Start":68.25499999104068,"End":69.04999999096617,"Duration":0.7949999999254942}],"exportCalls":{"__wasm_call_ctors":[{"Start":71.460000006482,"End":71.46499998634681,"Duration":0.004999979864805937}],"stackAlloc":[{"Start":71.54500001342967,"End":71.54500001342967,"Duration":0},{"Start":71.59000000683591,"End":71.59000000683591,"Duration":0}],"main":[{"Start":71.6649999958463,"End":135.50000003306195,"Duration":63.83500003721565}]},"importCalls":{},"functionNameObjects":[],"addExport":{},"addImport":{},"addInstantiate":{},"addInstantiateStreaming":{},"addCompile":{},"addCompileStreaming":{},"addFunctionNames":{}}},"addWasmFileReference":{}}],"CollectedLogs":["ALAN:  Compilation Time (Func #7):  0x3a88080a33b1 <String[16]: \"__errno_location\"> 4930683 ns (4.93068) mills\nALAN:  Instantiation Time (Func #7):  0x3a8808399309 <String[16]: \"__errno_location\"> 315925 ns (0.315925) mills\n","ALAN:  Compilation Time (Func #7):  0x1341080a33b1 <String[16]: \"__errno_location\"> 672086 ns (0.672086) mills\nALAN:  Instantiation Time (Func #7):  0x134108398dc1 <String[16]: \"__errno_location\"> 276701 ns (0.276701) mills\n"],"jsOutputRows":{"d9bcc02f1f1c5cf990bc2b0ef86dbe69d32bf7db37c27cffcb2e62848c6820f8":{"compile":[5.089999991469085,0.7949999999254942],"instantiate":[0.42500003473833203,0.375000003259629],"exports":{"__wasm_call_ctors":[0.004999979864805937,0.004999979864805937],"stackAlloc":[0,0],"main":[64.70499996794388,63.83500003721565]},"csvLines":"5.089999991469085,0.7949999999254942\n0.42500003473833203,0.375000003259629\n0.004999979864805937,0.004999979864805937\n64.70499996794388,63.83500003721565\n0,0\n","csvOrder":["compile","instantiate","__wasm_call_ctors","main","stackAlloc"]}},"cppOutputRows":{"__errno_location":{"compile":[4930683,672086],"instantiate":[315925,276701]}}},"O1":{"WebAssemblyCollectedTimes":[{"filesFound":0,"altered":true,"WasmFiles":{"d9bcc02f1f1c5cf990bc2b0ef86dbe69d32bf7db37c27cffcb2e62848c6820f8":{"instantiate":[{"Start":72.55000004079193,"End":72.92500004405156,"Duration":0.375000003259629}],"compile":[{"Start":70.38500002818182,"End":72.5100000272505,"Duration":2.1249999990686774}],"exportCalls":{"__wasm_call_ctors":[{"Start":74.4150000391528,"End":74.4150000391528,"Duration":0}],"stackAlloc":[{"Start":74.495000008028,"End":74.495000008028,"Duration":0},{"Start":74.53500002156943,"End":74.53500002156943,"Duration":0}],"main":[{"Start":74.61000001057982,"End":136.77500002086163,"Duration":62.1650000102818}]},"importCalls":{},"functionNameObjects":[],"addExport":{},"addImport":{},"addInstantiate":{},"addInstantiateStreaming":{},"addCompile":{},"addCompileStreaming":{},"addFunctionNames":{}}},"addWasmFileReference":{}},{"filesFound":0,"altered":true,"WasmFiles":{"d9bcc02f1f1c5cf990bc2b0ef86dbe69d32bf7db37c27cffcb2e62848c6820f8":{"instantiate":[{"Start":66.129999991972,"End":66.5150000131689,"Duration":0.3850000211969018}],"compile":[{"Start":61.35000003268942,"End":66.09000003663823,"Duration":4.740000003948808}],"exportCalls":{"__wasm_call_ctors":[{"Start":68.00999998813495,"End":68.00999998813495,"Duration":0}],"stackAlloc":[{"Start":68.085000035353,"End":68.09000001521781,"Duration":0.004999979864805937},{"Start":68.13500000862405,"End":68.13500000862405,"Duration":0}],"main":[{"Start":68.20999999763444,"End":129.26000001607463,"Duration":61.05000001844019}]},"importCalls":{},"functionNameObjects":[],"addExport":{},"addImport":{},"addInstantiate":{},"addInstantiateStreaming":{},"addCompile":{},"addCompileStreaming":{},"addFunctionNames":{}}},"addWasmFileReference":{}}],"CollectedLogs":["ALAN:  Compilation Time (Func #7):  0x1624080a33b1 <String[16]: \"__errno_location\"> 2017385 ns (2.01738) mills\nALAN:  Instantiation Time (Func #7):  0x162408398dc1 <String[16]: \"__errno_location\"> 280483 ns (0.280483) mills\n","ALAN:  Compilation Time (Func #7):  0x0b3c080a33b1 <String[16]: \"__errno_location\"> 4605288 ns (4.60529) mills\nALAN:  Instantiation Time (Func #7):  0x0b3c08399309 <String[16]: \"__errno_location\"> 290016 ns (0.290016) mills\n"],"jsOutputRows":{"d9bcc02f1f1c5cf990bc2b0ef86dbe69d32bf7db37c27cffcb2e62848c6820f8":{"compile":[2.1249999990686774,4.740000003948808],"instantiate":[0.375000003259629,0.3850000211969018],"exports":{"__wasm_call_ctors":[0,0],"stackAlloc":[0,0.004999979864805937],"main":[62.1650000102818,61.05000001844019]},"csvLines":"2.1249999990686774,4.740000003948808\n0.375000003259629,0.3850000211969018\n0,0\n62.1650000102818,61.05000001844019\n0,0.004999979864805937\n","csvOrder":["compile","instantiate","__wasm_call_ctors","main","stackAlloc"]}},"cppOutputRows":{"__errno_location":{"compile":[2017385,4605288],"instantiate":[280483,290016]}}},"O2":{"WebAssemblyCollectedTimes":[{"filesFound":0,"altered":true,"WasmFiles":{"d9bcc02f1f1c5cf990bc2b0ef86dbe69d32bf7db37c27cffcb2e62848c6820f8":{"instantiate":[{"Start":70.55000000400469,"End":71.05500000761822,"Duration":0.5050000036135316}],"compile":[{"Start":67.66999996034428,"End":70.50500001059845,"Duration":2.835000050254166}],"exportCalls":{"__wasm_call_ctors":[{"Start":72.66499998513609,"End":72.66499998513609,"Duration":0}],"stackAlloc":[{"Start":72.74500001221895,"End":72.74500001221895,"Duration":0},{"Start":72.78499996755272,"End":72.79000000562519,"Duration":0.00500003807246685}],"main":[{"Start":72.86499999463558,"End":133.3849999937229,"Duration":60.519999999087304}]},"importCalls":{},"functionNameObjects":[],"addExport":{},"addImport":{},"addInstantiate":{},"addInstantiateStreaming":{},"addCompile":{},"addCompileStreaming":{},"addFunctionNames":{}}},"addWasmFileReference":{}},{"filesFound":0,"altered":true,"WasmFiles":{"d9bcc02f1f1c5cf990bc2b0ef86dbe69d32bf7db37c27cffcb2e62848c6820f8":{"instantiate":[{"Start":76.1900000507012,"End":76.58500003162771,"Duration":0.39499998092651367}],"compile":[{"Start":71.30000001052395,"End":76.15000003715977,"Duration":4.850000026635826}],"exportCalls":{"__wasm_call_ctors":[{"Start":78.11500004027039,"End":78.11500004027039,"Duration":0}],"stackAlloc":[{"Start":78.19500000914559,"End":78.19500000914559,"Duration":0},{"Start":78.24000000255182,"End":78.24000000255182,"Duration":0}],"main":[{"Start":78.32000002963468,"End":142.28000002913177,"Duration":63.959999999497086}]},"importCalls":{},"functionNameObjects":[],"addExport":{},"addImport":{},"addInstantiate":{},"addInstantiateStreaming":{},"addCompile":{},"addCompileStreaming":{},"addFunctionNames":{}}},"addWasmFileReference":{}}],"CollectedLogs":["ALAN:  Compilation Time (Func #7):  0x2207080a33b1 <String[16]: \"__errno_location\"> 2687097 ns (2.6871) mills\nALAN:  Instantiation Time (Func #7):  0x220708398dc1 <String[16]: \"__errno_location\"> 368419 ns (0.368419) mills\n","ALAN:  Compilation Time (Func #7):  0x29ed080a33b1 <String[16]: \"__errno_location\"> 4714480 ns (4.71448) mills\nALAN:  Instantiation Time (Func #7):  0x29ed08398dc1 <String[16]: \"__errno_location\"> 288707 ns (0.288707) mills\n"],"jsOutputRows":{"d9bcc02f1f1c5cf990bc2b0ef86dbe69d32bf7db37c27cffcb2e62848c6820f8":{"compile":[2.835000050254166,4.850000026635826],"instantiate":[0.5050000036135316,0.39499998092651367],"exports":{"__wasm_call_ctors":[0,0],"stackAlloc":[0,0],"main":[60.519999999087304,63.959999999497086]},"csvLines":"2.835000050254166,4.850000026635826\n0.5050000036135316,0.39499998092651367\n0,0\n60.519999999087304,63.959999999497086\n0,0\n","csvOrder":["compile","instantiate","__wasm_call_ctors","main","stackAlloc"]}},"cppOutputRows":{"__errno_location":{"compile":[2687097,4714480],"instantiate":[368419,288707]}}},"O3":{"WebAssemblyCollectedTimes":[{"filesFound":0,"altered":true,"WasmFiles":{"d9bcc02f1f1c5cf990bc2b0ef86dbe69d32bf7db37c27cffcb2e62848c6820f8":{"instantiate":[{"Start":63.58499999623746,"End":64.17999998666346,"Duration":0.5949999904260039}],"compile":[{"Start":58.29999997513369,"End":63.54000000283122,"Duration":5.240000027697533}],"exportCalls":{"__wasm_call_ctors":[{"Start":65.82499999785796,"End":65.82499999785796,"Duration":0}],"stackAlloc":[{"Start":65.95000001834705,"End":65.95000001834705,"Duration":0},{"Start":66.01499998942018,"End":66.01499998942018,"Duration":0}],"main":[{"Start":66.1250000121072,"End":139.37499996973202,"Duration":73.24999995762482}]},"importCalls":{},"functionNameObjects":[],"addExport":{},"addImport":{},"addInstantiate":{},"addInstantiateStreaming":{},"addCompile":{},"addCompileStreaming":{},"addFunctionNames":{}}},"addWasmFileReference":{}},{"filesFound":0,"altered":true,"WasmFiles":{"d9bcc02f1f1c5cf990bc2b0ef86dbe69d32bf7db37c27cffcb2e62848c6820f8":{"instantiate":[{"Start":67.47000000905246,"End":68.01500002620742,"Duration":0.5450000171549618}],"compile":[{"Start":62.105000019073486,"End":67.42000003578141,"Duration":5.315000016707927}],"exportCalls":{"__wasm_call_ctors":[{"Start":69.675000035204,"End":69.675000035204,"Duration":0}],"stackAlloc":[{"Start":69.78499999968335,"End":69.79000003775582,"Duration":0.00500003807246685},{"Start":69.84500004909933,"End":69.85000002896413,"Duration":0.004999979864805937}],"main":[{"Start":69.95000003371388,"End":146.85499999905005,"Duration":76.90499996533617}]},"importCalls":{},"functionNameObjects":[],"addExport":{},"addImport":{},"addInstantiate":{},"addInstantiateStreaming":{},"addCompile":{},"addCompileStreaming":{},"addFunctionNames":{}}},"addWasmFileReference":{}}],"CollectedLogs":["ALAN:  Compilation Time (Func #7):  0x23bd080a33b1 <String[16]: \"__errno_location\"> 5068411 ns (5.06841) mills\nALAN:  Instantiation Time (Func #7):  0x23bd08398dc1 <String[16]: \"__errno_location\"> 437158 ns (0.437158) mills\n","ALAN:  Compilation Time (Func #7):  0x2e27080a33b1 <String[16]: \"__errno_location\"> 5141473 ns (5.14147) mills\nALAN:  Instantiation Time (Func #7):  0x2e2708398dc1 <String[16]: \"__errno_location\"> 409074 ns (0.409074) mills\n"],"jsOutputRows":{"d9bcc02f1f1c5cf990bc2b0ef86dbe69d32bf7db37c27cffcb2e62848c6820f8":{"compile":[5.240000027697533,5.315000016707927],"instantiate":[0.5949999904260039,0.5450000171549618],"exports":{"__wasm_call_ctors":[0,0],"stackAlloc":[0,0.00500003807246685],"main":[73.24999995762482,76.90499996533617]},"csvLines":"5.240000027697533,5.315000016707927\n0.5949999904260039,0.5450000171549618\n0,0\n73.24999995762482,76.90499996533617\n0,0.00500003807246685\n","csvOrder":["compile","instantiate","__wasm_call_ctors","main","stackAlloc"]}},"cppOutputRows":{"__errno_location":{"compile":[5068411,5141473],"instantiate":[437158,409074]}}},"Os":{"WebAssemblyCollectedTimes":[{"filesFound":0,"altered":true,"WasmFiles":{"d9bcc02f1f1c5cf990bc2b0ef86dbe69d32bf7db37c27cffcb2e62848c6820f8":{"instantiate":[{"Start":90.83499998087063,"End":91.19999996619299,"Duration":0.3649999853223562}],"compile":[{"Start":89.85999994911253,"End":90.79999994719401,"Duration":0.9399999980814755}],"exportCalls":{"__wasm_call_ctors":[{"Start":92.91499998653308,"End":92.91499998653308,"Duration":0}],"stackAlloc":[{"Start":92.99499995540828,"End":92.99499995540828,"Duration":0},{"Start":93.0349999689497,"End":93.0349999689497,"Duration":0}],"main":[{"Start":93.11499999603257,"End":153.33499998087063,"Duration":60.21999998483807}]},"importCalls":{},"functionNameObjects":[],"addExport":{},"addImport":{},"addInstantiate":{},"addInstantiateStreaming":{},"addCompile":{},"addCompileStreaming":{},"addFunctionNames":{}}},"addWasmFileReference":{}},{"filesFound":0,"altered":true,"WasmFiles":{"d9bcc02f1f1c5cf990bc2b0ef86dbe69d32bf7db37c27cffcb2e62848c6820f8":{"instantiate":[{"Start":64.59500000346452,"End":65.11000002501532,"Duration":0.5150000215508044}],"compile":[{"Start":59.69500000355765,"End":64.55000001005828,"Duration":4.855000006500632}],"exportCalls":{"__wasm_call_ctors":[{"Start":66.724999982398,"End":66.73000002047047,"Duration":0.00500003807246685}],"stackAlloc":[{"Start":66.83000002522022,"End":66.83000002522022,"Duration":0},{"Start":66.89000001642853,"End":66.89000001642853,"Duration":0}],"main":[{"Start":66.99000002117828,"End":140.27500001247972,"Duration":73.28499999130145}]},"importCalls":{},"functionNameObjects":[],"addExport":{},"addImport":{},"addInstantiate":{},"addInstantiateStreaming":{},"addCompile":{},"addCompileStreaming":{},"addFunctionNames":{}}},"addWasmFileReference":{}}],"CollectedLogs":["ALAN:  Compilation Time (Func #7):  0x0f00080a33b1 <String[16]: \"__errno_location\"> 829807 ns (0.829807) mills\nALAN:  Instantiation Time (Func #7):  0x0f0008398dc1 <String[16]: \"__errno_location\"> 269498 ns (0.269498) mills\n","ALAN:  Compilation Time (Func #7):  0x3639080a33b1 <String[16]: \"__errno_location\"> 4698728 ns (4.69873) mills\nALAN:  Instantiation Time (Func #7):  0x363908398dc1 <String[16]: \"__errno_location\"> 374043 ns (0.374043) mills\n"],"jsOutputRows":{"d9bcc02f1f1c5cf990bc2b0ef86dbe69d32bf7db37c27cffcb2e62848c6820f8":{"compile":[0.9399999980814755,4.855000006500632],"instantiate":[0.3649999853223562,0.5150000215508044],"exports":{"__wasm_call_ctors":[0,0.00500003807246685],"stackAlloc":[0,0],"main":[60.21999998483807,73.28499999130145]},"csvLines":"0.9399999980814755,4.855000006500632\n0.3649999853223562,0.5150000215508044\n0,0.00500003807246685\n60.21999998483807,73.28499999130145\n0,0\n","csvOrder":["compile","instantiate","__wasm_call_ctors","main","stackAlloc"]}},"cppOutputRows":{"__errno_location":{"compile":[829807,4698728],"instantiate":[269498,374043]}}},"Oz":{"WebAssemblyCollectedTimes":[{"filesFound":0,"altered":true,"WasmFiles":{"d9bcc02f1f1c5cf990bc2b0ef86dbe69d32bf7db37c27cffcb2e62848c6820f8":{"instantiate":[{"Start":68.20500001776963,"End":68.61499999649823,"Duration":0.4099999787285924}],"compile":[{"Start":63.695000018924475,"End":68.16999998409301,"Duration":4.474999965168536}],"exportCalls":{"__wasm_call_ctors":[{"Start":70.10499999159947,"End":70.10499999159947,"Duration":0}],"stackAlloc":[{"Start":70.17999998060986,"End":70.17999998060986,"Duration":0},{"Start":70.2249999740161,"End":70.2249999740161,"Duration":0}],"main":[{"Start":70.29499998316169,"End":134.6250000060536,"Duration":64.33000002289191}]},"importCalls":{},"functionNameObjects":[],"addExport":{},"addImport":{},"addInstantiate":{},"addInstantiateStreaming":{},"addCompile":{},"addCompileStreaming":{},"addFunctionNames":{}}},"addWasmFileReference":{}},{"filesFound":0,"altered":true,"WasmFiles":{"d9bcc02f1f1c5cf990bc2b0ef86dbe69d32bf7db37c27cffcb2e62848c6820f8":{"instantiate":[{"Start":76.0899999877438,"End":76.8149999785237,"Duration":0.7249999907799065}],"compile":[{"Start":72.78499996755272,"End":76.01999997859821,"Duration":3.2350000110454857}],"exportCalls":{"__wasm_call_ctors":[{"Start":78.68499995674938,"End":78.68999999482185,"Duration":0.00500003807246685}],"stackAlloc":[{"Start":78.83499999297783,"End":78.83999997284263,"Duration":0.004999979864805937},{"Start":78.9199999999255,"End":78.9199999999255,"Duration":0}],"main":[{"Start":79.05999996000901,"End":142.10999995702878,"Duration":63.04999999701977}]},"importCalls":{},"functionNameObjects":[],"addExport":{},"addImport":{},"addInstantiate":{},"addInstantiateStreaming":{},"addCompile":{},"addCompileStreaming":{},"addFunctionNames":{}}},"addWasmFileReference":{}}],"CollectedLogs":["ALAN:  Compilation Time (Func #7):  0x0d73080a33b1 <String[16]: \"__errno_location\"> 4340594 ns (4.34059) mills\nALAN:  Instantiation Time (Func #7):  0x0d7308398dc1 <String[16]: \"__errno_location\"> 305301 ns (0.305301) mills\n","ALAN:  Compilation Time (Func #7):  0x3b5b080a33b1 <String[16]: \"__errno_location\"> 3055261 ns (3.05526) mills\nALAN:  Instantiation Time (Func #7):  0x3b5b08399315 <String[16]: \"__errno_location\"> 544497 ns (0.544497) mills\n"],"jsOutputRows":{"d9bcc02f1f1c5cf990bc2b0ef86dbe69d32bf7db37c27cffcb2e62848c6820f8":{"compile":[4.474999965168536,3.2350000110454857],"instantiate":[0.4099999787285924,0.7249999907799065],"exports":{"__wasm_call_ctors":[0,0.00500003807246685],"stackAlloc":[0,0.004999979864805937],"main":[64.33000002289191,63.04999999701977]},"csvLines":"4.474999965168536,3.2350000110454857\n0.4099999787285924,0.7249999907799065\n0,0.00500003807246685\n64.33000002289191,63.04999999701977\n0,0.004999979864805937\n","csvOrder":["compile","instantiate","__wasm_call_ctors","main","stackAlloc"]}},"cppOutputRows":{"__errno_location":{"compile":[4340594,3055261],"instantiate":[305301,544497]}}}}